<annotation>
    <folder>7000</folder>
    <filename>Numazu_20170906094555.jpg</filename>
    <size>
        <width>600</width>
        <height>600</height>
        <depth>3</depth>
    </size>
    <segmented>0</segmented>
    <object>
        <name>D01</name>
        <pose>Unspecified</pose>
        <truncated>0</truncated>
        <difficult>0</difficult>
        <bndbox>
            <xmin>316</xmin>
            <ymin>317</ymin>
            <xmax>532</xmax>
            <ymax>572</ymax>
        </bndbox>
    </object>
    <object>
        <name>D44</name>
        <pose>Unspecified</pose>
        <truncated>0</truncated>
        <difficult>0</difficult>
        <bndbox>
            <xmin>294</xmin>
            <ymin>264</ymin>
            <xmax>600</xmax>
            <ymax>579</ymax>
        </bndbox>
    </object>
</annotation>