<annotation>
    <folder>Adachi</folder>
    <filename>Adachi_20170907134735.jpg</filename>
    <size>
        <width>600</width>
        <height>600</height>
    </size>
    <segmented>0</segmented>
    <object>
        <name>D10</name>
        <bndbox>
            <xmin>236</xmin>
            <ymin>255</ymin>
            <xmax>429</xmax>
            <ymax>305</ymax>
        </bndbox>
    </object>
    <object>
        <name>D43</name>
        <bndbox>
            <xmin>7</xmin>
            <ymin>318</ymin>
            <xmax>596</xmax>
            <ymax>589</ymax>
        </bndbox>
    </object>
</annotation>