<annotation>
    <folder>Nagakute</folder>
    <filename>Nagakute_20170907151419.jpg</filename>
    <size>
        <width>600</width>
        <height>600</height>
        <depth>3</depth>
    </size>
    <segmented>0</segmented>
    <object>
        <name>D44</name>
        <pose>Unspecified</pose>
        <truncated>0</truncated>
        <difficult>0</difficult>
        <bndbox>
            <xmin>283</xmin>
            <ymin>385</ymin>
            <xmax>481</xmax>
            <ymax>596</ymax>
        </bndbox>
    </object>
    <object>
        <name>D00</name>
        <pose>Unspecified</pose>
        <truncated>0</truncated>
        <difficult>0</difficult>
        <bndbox>
            <xmin>236</xmin>
            <ymin>423</ymin>
            <xmax>323</xmax>
            <ymax>589</ymax>
        </bndbox>
    </object>
</annotation>